adaptivetesting/__init__.py
adaptivetesting/data/__csv_context.py
adaptivetesting/data/__init__.py
adaptivetesting/data/__pickle_context.py
adaptivetesting/implementations/__default_implementation.py
adaptivetesting/implementations/__init__.py
adaptivetesting/implementations/__pre_test.py
adaptivetesting/implementations/__semi_implementation.py
adaptivetesting/implementations/__test_assembler.py
adaptivetesting/math/__gen_response_pattern.py
adaptivetesting/math/__init__.py
adaptivetesting/math/estimators/__bayes_modal_estimation.py
adaptivetesting/math/estimators/__expect_a_posteriori.py
adaptivetesting/math/estimators/__init__.py
adaptivetesting/math/estimators/__ml_estimation.py
adaptivetesting/math/estimators/__prior.py
adaptivetesting/math/estimators/__test_information.py
adaptivetesting/math/estimators/__functions/__bayes.py
adaptivetesting/math/estimators/__functions/__estimators.py
adaptivetesting/math/item_selection/__init__.py
adaptivetesting/math/item_selection/__maximum_information_criterion.py
adaptivetesting/math/item_selection/__urrys_rule.py
adaptivetesting/models/__adaptive_test.py
adaptivetesting/models/__algorithm_exception.py
adaptivetesting/models/__init__.py
adaptivetesting/models/__item_pool.py
adaptivetesting/models/__item_selection_exception.py
adaptivetesting/models/__misc.py
adaptivetesting/models/__test_item.py
adaptivetesting/models/__test_result.py
adaptivetesting/services/__estimator_interface.py
adaptivetesting/services/__init__.py
adaptivetesting/services/__item_selection_protocol.py
adaptivetesting/services/__test_results_interface.py
adaptivetesting/simulation/__init__.py
adaptivetesting/simulation/__simulation.py
adaptivetesting/tests/__init__.py
adaptivetesting/tests/test_adaptive_test.py
adaptivetesting/tests/test_bayes_modal.py
adaptivetesting/tests/test_descriptives.py
adaptivetesting/tests/test_eap.py
adaptivetesting/tests/test_generate_response_pattern.py
adaptivetesting/tests/test_information_test.py
adaptivetesting-1.1.5.dist-info/METADATA
adaptivetesting-1.1.5.dist-info/WHEEL
adaptivetesting-1.1.5.dist-info/licenses/LICENSE
adaptivetesting-1.1.5.dist-info/RECORD
