Metadata-Version: 2.4
Name: adaptivetesting
Version: 1.1.5
Summary: adaptivetesting is a Python package that can be used to simulate and evaluate custom CAT scenarios as well as implement them in real-world testing scenarios from a single codebase
Project-URL: Homepage, https://github.com/condecon/adaptivetesting
Project-URL: Documentation, https://github.com/condecon/adaptivetesting/tree/main/docs
Project-URL: Repository, https://github.com/condecon/adaptivetesting.git
Project-URL: Issues, https://github.com/condecon/adaptivetesting/issues
Author-email: Jonas Engicht <dev@condecon.de>
License-File: LICENSE
Keywords: computerized-adaptive-testing,item-response-theory,psychology,statistics
Requires-Python: >=3.12
Requires-Dist: matplotlib>=3.9.0
Requires-Dist: numpy>=2.0.0
Requires-Dist: pandas>=2.2.0
Requires-Dist: scipy>=1.12.0
Requires-Dist: tqdm>=4.66.0
